<?xml version="1.0" encoding="UTF-8"?>
<root>
    <configurations>
        <config id="1">
            <buttons>
                <button type="switch" instrument="turnkey" parameter="Reset" inverted="True" text="Start working" />
                <button type="switch" instrument="turnkey" parameter="mode" inverted="False" text="Manual sweeping" />
            </buttons>
        </config>
        <config id="8">
            <buttons>
                <button type="switch" instrument="PID" parameter="mode" inverted="False" text="Ready for trigger" />
                <button type="switch" instrument="PID" parameter="slow_PID_Reset" inverted="True" text="slow PID" />
                <button type="switch" instrument="PID" parameter="fast_PID_Reset" inverted="True" text="fast PID" />
            </buttons>
        </config>
        <config id="9">
            <buttons>
                <button type="switch" instrument="feedback" parameter="LO_Reset" inverted="True" text="Enable LO" />
                <button type="switch" instrument="feedback" parameter="slow_PID_Reset" inverted="True" text="slow PID" />
                <button type="switch" instrument="feedback" parameter="fast_PID_Reset" inverted="True" text="fast PID" />
            </buttons>
        </config>
        <config id="10">
            <buttons>
                <button type="switch" instrument="PID" parameter="mode" inverted="False" text="Ready for trigger" />
                <button type="switch" instrument="PID" parameter="slow_PID_Reset" inverted="True" text="778 slow PID" />
                <button type="switch" instrument="PID" parameter="fast_PID_Reset" inverted="True" text="778 fast PID" />
                <button type="switch" instrument="feedback" parameter="LO_Reset" inverted="True" text="Enable LO" />
                <button type="switch" instrument="feedback" parameter="slow_PID_Reset" inverted="True" text="1556 slow PID" />
                <button type="switch" instrument="feedback" parameter="fast_PID_Reset" inverted="True" text="1556 fast PID" />
            </buttons>
        </config>
	    <config id="6">
            <buttons>
                <button type="switch" instrument="PID" parameter="Reset" inverted="True" text="Enable PID" />
            </buttons>
        </config>
        <config id="11">
            <buttons>
                <button type="switch" instrument="PID" parameter="Reset" inverted="True" text="Enable PID" />
            </buttons>
        </config>
        <config id="12">
            <buttons>
                <button type="switch" instrument="PDH" parameter="write_enable" inverted="False" text="RAM write enable" />
                <button type="script" instrument="PDH" script="upload_parameter_4SLA_IIR" text="Upload PDH parameters" />
            </buttons>
        </config>
    </configurations>
</root>
